setup.py
pyagram/__init__.py
pyagram/diagram.py
pyagram/entity_relationship_diagram.py
pyagram/pyagram.py
pyagram/state_transition_diagram.py
pyagram.egg-info/PKG-INFO
pyagram.egg-info/SOURCES.txt
pyagram.egg-info/dependency_links.txt
pyagram.egg-info/entry_points.txt
pyagram.egg-info/requires.txt
pyagram.egg-info/top_level.txt