Metadata-Version: 1.1
Name: pyagram
Version: 1.4.3
Summary: Pyagram: Diagram Generator
Home-page: https://github.com/hideshi
Author: Hideshi Ogoshi
Author-email: hideshi.ogoshi@gmail.com
License: MIT License
Platform: MacOS
Classifier: Development Status :: 5 - Production/Stable
Classifier: Intended Audience :: Developers
Classifier: Intended Audience :: Information Technology
Classifier: License :: OSI Approved :: MIT License
Classifier: Operating System :: MacOS :: MacOS X
Classifier: Operating System :: Microsoft :: Windows
Classifier: Programming Language :: Python :: 3.5
Classifier: Topic :: Documentation
Classifier: Topic :: Software Development :: Code Generators
Classifier: Topic :: Software Development :: Documentation
